pilotis_io_aws/__init__.py
pilotis_io_aws/__version__.py
pilotis_io_aws/s3/__init__.py
pilotis_io_aws/s3/s3_io_api.py
pilotis_io_aws/s3/s3_numpy_api.py
pilotis_io_aws/s3/s3_pandas_api.py
pilotis_io_aws-0.2.0.dist-info/LICENSE
pilotis_io_aws-0.2.0.dist-info/WHEEL
pilotis_io_aws-0.2.0.dist-info/METADATA
pilotis_io_aws-0.2.0.dist-info/RECORD
